faridasuselessproject/__init__.py
faridasuselessproject-0.1.5.dist-info/METADATA
faridasuselessproject-0.1.5.dist-info/WHEEL
faridasuselessproject-0.1.5.dist-info/top_level.txt
faridasuselessproject-0.1.5.dist-info/RECORD
